{"id": "itsdangerous.timed", "path": "c:\\Users\\bruno\\Downloads\\TCC\\App\\venv\\lib\\site-packages\\itsdangerous\\timed.py", "mtime": 1623949354, "size": 7850, "hash": "bdbf81679ed6c87775861f606d769ee2a66128da99202b837e52c835cb29f626", "data_mtime": 1623890250, "dependencies": ["time", "typing", "datetime", "itsdangerous.encoding", "itsdangerous.exc", "itsdangerous.serializer", "itsdangerous.signer", "typing_extensions", "builtins", "abc"], "suppressed": [], "options": {"warn_unused_ignores": false, "platform": "win32", "disallow_subclassing_any": false, "ignore_errors": false, "local_partial_types": false, "allow_redefinition": false, "check_untyped_defs": false, "warn_unreachable": false, "ignore_missing_imports": true, "implicit_reexport": true, "strict_optional_whitelist": null, "disallow_any_decorated": false, "show_none_errors": true, "strict_optional": true, "disallow_any_unimported": false, "disallow_untyped_calls": false, "always_false": [], "follow_imports": "silent", "disallow_any_explicit": false, "disallow_incomplete_defs": false, "bazel": false, "warn_no_return": true, "disallow_untyped_decorators": false, "always_true": [], "plugins": [], "disallow_any_expr": false, "no_implicit_optional": false, "warn_return_any": false, "mypyc": false, "follow_imports_for_stubs": false, "allow_untyped_globals": false, "disallow_any_generics": false, "strict_equality": false, "disallow_untyped_defs": false}, "dep_prios": [10, 10, 5, 5, 5, 5, 5, 25, 5, 30], "dep_lines": [1, 2, 4, 7, 12, 15, 16, 23, 1, 1], "interface_hash": "28f40ab2bd766f6d46750ecdf205b8b8cd54ecce79f615ff6bfa0c1c482d7628", "version_id": "0.902", "ignore_all": true, "plugin_data": null}